wagtailthemes/__init__.py
wagtailthemes/loaders.py
wagtailthemes/middleware.py
wagtailthemes/models.py
wagtailthemes/thread.py
wagtailthemes/__pycache__/__init__.cpython-39.pyc
wagtailthemes/__pycache__/cache.cpython-39.pyc
wagtailthemes/__pycache__/forms.cpython-39.pyc
wagtailthemes/__pycache__/loaders.cpython-39.pyc
wagtailthemes/__pycache__/middleware.cpython-39.pyc
wagtailthemes/__pycache__/models.cpython-39.pyc
wagtailthemes/__pycache__/settings.cpython-39.pyc
wagtailthemes/__pycache__/storage.cpython-39.pyc
wagtailthemes/__pycache__/thread.cpython-39.pyc
wagtailthemes/__pycache__/utils.cpython-39.pyc
wagtailthemes/__pycache__/views.cpython-39.pyc
wagtailthemes/__pycache__/wagtail_hooks.cpython-39.pyc
wagtailthemes/contrib/__pycache__/__init__.cpython-39.pyc
wagtailthemes/contrib/aws/__pycache__/__init__.cpython-39.pyc
wagtailthemes/contrib/aws/__pycache__/storage.cpython-39.pyc
wagtailthemes/management/commands/__pycache__/import_theme.cpython-39.pyc
wagtailthemes/migrations/0001_initial.py
wagtailthemes/migrations/0002_auto_20161124_1107.py
wagtailthemes/migrations/__init__.py
wagtailthemes/migrations/__pycache__/0001_initial.cpython-39.pyc
wagtailthemes/migrations/__pycache__/0002_auto_20161124_1107.cpython-39.pyc
wagtailthemes/migrations/__pycache__/0003_auto_20220829_1325.cpython-39.pyc
wagtailthemes/migrations/__pycache__/0003_auto_20220829_1339.cpython-39.pyc
wagtailthemes/migrations/__pycache__/0003_auto_20220829_1350.cpython-39.pyc
wagtailthemes/migrations/__pycache__/0003_auto_20220829_1431.cpython-39.pyc
wagtailthemes/migrations/__pycache__/0004_auto_20220830_1603.cpython-39.pyc
wagtailthemes/migrations/__pycache__/0005_alter_staticfile_id_alter_template_id_alter_theme_id.cpython-39.pyc
wagtailthemes/migrations/__pycache__/__init__.cpython-39.pyc
wagtailthemes/templatetags/__pycache__/__init__.cpython-39.pyc
wagtailthemes/templatetags/__pycache__/theme.cpython-39.pyc
wagtailthemes/templatetags/__pycache__/themes.cpython-39.pyc
wagtail_themes-0.5.0.dist-info/LICENSE
wagtail_themes-0.5.0.dist-info/METADATA
wagtail_themes-0.5.0.dist-info/WHEEL
wagtail_themes-0.5.0.dist-info/top_level.txt
wagtail_themes-0.5.0.dist-info/RECORD
