Metadata-Version: 2.1
Name: wagtail-themes
Version: 0.5.0
Summary: Site specific theme loader for Django Wagtail.
Home-page: https://github.com/moorinl/wagtail-themes
Author: Rob Moorman
Author-email: rob@moori.nl
License: MIT
Classifier: Environment :: Web Environment
Classifier: Framework :: Django
Classifier: Operating System :: Unix
Classifier: Framework :: Wagtail
Classifier: Framework :: Wagtail :: 3
Classifier: Framework :: Wagtail :: 4
Classifier: Framework :: Wagtail :: 5
Classifier: Programming Language :: Python :: 3
Classifier: Programming Language :: Python :: 3.8
Classifier: Programming Language :: Python :: 3.9
Classifier: Programming Language :: Python :: 3.10
Classifier: Programming Language :: Python :: 3.11
License-File: LICENSE
Requires-Dist: django (>=4.2)
Requires-Dist: wagtail (>=5.0)
Provides-Extra: test
Requires-Dist: flake8 ; extra == 'test'
Requires-Dist: isort ; extra == 'test'
Requires-Dist: pytest ; extra == 'test'
Requires-Dist: pytest-cov ; extra == 'test'
Requires-Dist: pytest-django ; extra == 'test'
Requires-Dist: wagtail ; extra == 'test'
